odoo/addons/l10n_us_gaap/README.rst
odoo/addons/l10n_us_gaap/__init__.py
odoo/addons/l10n_us_gaap/__manifest__.py
odoo/addons/l10n_us_gaap/data/account_chart_template_data.xml
odoo/addons/l10n_us_gaap/data/account_chart_template_data_load.xml
odoo/addons/l10n_us_gaap/data/account_group.xml
odoo/addons/l10n_us_gaap/data/account_us_gaap_data.xml
odoo/addons/l10n_us_gaap/data/res_company_data.xml
odoo/addons/l10n_us_gaap/docs/l10n_us_gaap_trial_balance.ods
odoo/addons/l10n_us_gaap/i18n/l10n_us_gaap.pot
odoo/addons/l10n_us_gaap/readme/CONTRIBUTORS.rst
odoo/addons/l10n_us_gaap/readme/DESCRIPTION.rst
odoo/addons/l10n_us_gaap/readme/INSTALL.rst
odoo/addons/l10n_us_gaap/readme/USAGE.rst
odoo/addons/l10n_us_gaap/static/description/icon.png
odoo/addons/l10n_us_gaap/static/description/index.html
odoo/addons/l10n_us_gaap/tests/__init__.py
odoo/addons/l10n_us_gaap/tests/test_base_us.py
odoo/addons/l10n_us_gaap/views/res_partner_bank_views.xml
odoo12_addon_l10n_us_gaap-12.0.1.1.0.dist-info/METADATA
odoo12_addon_l10n_us_gaap-12.0.1.1.0.dist-info/WHEEL
odoo12_addon_l10n_us_gaap-12.0.1.1.0.dist-info/top_level.txt
odoo12_addon_l10n_us_gaap-12.0.1.1.0.dist-info/RECORD
